iicsapi/__init__.py
iicsapi/client.py
iicsapi/exceptions.py
iicsapi/nodes/__init__.py
iicsapi/nodes/component.py
iicsapi-2.1.2.dist-info/licenses/LICENSE
iicsapi-2.1.2.dist-info/METADATA
iicsapi-2.1.2.dist-info/WHEEL
iicsapi-2.1.2.dist-info/top_level.txt
iicsapi-2.1.2.dist-info/RECORD
